saltext/mqtt_return/__init__.py
saltext/mqtt_return/version.py
saltext/mqtt_return/returners/__init__.py
saltext/mqtt_return/returners/mqtt_return_mod.py
saltext/mqtt_return/utils/awsiot.py
saltext/mqtt_return/utils/mqtt.py
saltext/mqtt_return/utils/mqtt_queue.py
saltext_mqtt_return-1.3.1.dist-info/LICENSE
saltext_mqtt_return-1.3.1.dist-info/METADATA
saltext_mqtt_return-1.3.1.dist-info/NOTICE
saltext_mqtt_return-1.3.1.dist-info/WHEEL
saltext_mqtt_return-1.3.1.dist-info/entry_points.txt
saltext_mqtt_return-1.3.1.dist-info/top_level.txt
saltext_mqtt_return-1.3.1.dist-info/RECORD
